make_aggrid/__init__.py
make_aggrid-0.1.8.dist-info/LICENSE
make_aggrid-0.1.8.dist-info/METADATA
make_aggrid-0.1.8.dist-info/WHEEL
make_aggrid-0.1.8.dist-info/RECORD
