Metadata-Version: 2.3
Name: make-aggrid
Version: 0.1.8
Summary: Configura automaticamente o AgGrid no Streamlit com base em um DataFrame
License: MIT
Keywords: streamlit,aggrid,pandas,dataframe
Author: edwdev
Author-email: edjdevel@gmail.com
Requires-Python: >=3.10,<4.0
Classifier: Development Status :: 4 - Beta
Classifier: License :: OSI Approved :: MIT License
Classifier: Operating System :: OS Independent
Classifier: Programming Language :: Python :: 3
Classifier: Programming Language :: Python :: 3.10
Classifier: Programming Language :: Python :: 3.11
Classifier: Programming Language :: Python :: 3.12
Classifier: Programming Language :: Python :: 3.13
Requires-Dist: streamlit-aggrid (==1.1.2)
Project-URL: Documentation, https://github.com/edwdev-oficial/make-aggrid/blob/main/CHANGELOG.md
Project-URL: Homepage, https://github.com/edwdev-oficial/make-aggrid
Project-URL: Repository, https://github.com/edwdev-oficial/make-aggrid
